_tests/__init__.py
_tests/run_napari.py
_tests/test_gemspa_locate_worker.py
napari_gemspa/__init__.py
napari_gemspa/_gemspa_analyze_widget.py
napari_gemspa/_gemspa_data_views.py
napari_gemspa/_gemspa_file_import_widget.py
napari_gemspa/_gemspa_filter_links_widget.py
napari_gemspa/_gemspa_link_widget.py
napari_gemspa/_gemspa_locate_widget.py
napari_gemspa/_gemspa_plugin.py
napari_gemspa/_gemspa_widget.py
napari_gemspa/_reader.py
napari_gemspa/_utils.py
napari_gemspa/_writer.py
napari_gemspa/napari.yaml
napari_gemspa-0.0.4.dist-info/LICENSE
napari_gemspa-0.0.4.dist-info/METADATA
napari_gemspa-0.0.4.dist-info/WHEEL
napari_gemspa-0.0.4.dist-info/entry_points.txt
napari_gemspa-0.0.4.dist-info/top_level.txt
napari_gemspa-0.0.4.dist-info/RECORD
