Metadata-Version: 2.1
Name: napari-gemspa
Version: 0.0.4
Summary: A plugin for analysis of single particle tracking experiments
Home-page: https://github.com/liamholtlab/napari-gemspa
Author: Sarah Keegan
Author-email: sarah.keegan@nyulangone.org
License: BSD-3-Clause
Project-URL: Bug Tracker, https://github.com/liamholtlab/napari-gemspa/issues
Project-URL: Documentation, https://github.com/liamholtlab/napari-gemspa#README.md
Project-URL: Source Code, https://github.com/liamholtlab/napari-gemspa
Project-URL: User Support, https://github.com/liamholtlab/napari-gemspa/issues
Classifier: Development Status :: 2 - Pre-Alpha
Classifier: Framework :: napari
Classifier: Intended Audience :: Developers
Classifier: License :: OSI Approved :: BSD License
Classifier: Operating System :: OS Independent
Classifier: Programming Language :: Python
Classifier: Programming Language :: Python :: 3
Classifier: Programming Language :: Python :: 3 :: Only
Classifier: Programming Language :: Python :: 3.8
Classifier: Programming Language :: Python :: 3.9
Classifier: Programming Language :: Python :: 3.10
Classifier: Topic :: Scientific/Engineering :: Image Processing
Requires-Python: >=3.8
License-File: LICENSE
Requires-Dist: numpy
Requires-Dist: magicgui
Requires-Dist: qtpy
Requires-Dist: pandas
Requires-Dist: napari
Requires-Dist: scikit-image
Requires-Dist: gemspa-spt
Requires-Dist: matplotlib
Requires-Dist: trackpy
Requires-Dist: nd2
Provides-Extra: testing
Requires-Dist: tox ; extra == 'testing'
Requires-Dist: pytest ; extra == 'testing'
Requires-Dist: pytest-cov ; extra == 'testing'
Requires-Dist: pytest-qt ; extra == 'testing'
Requires-Dist: napari ; extra == 'testing'
Requires-Dist: pyqt5 ; extra == 'testing'
